Day 2/2:1mux/twotoone.v
module twotoone(
input in1,in2,
input sel,
output out
);


assign out =sel? in2:in1;


endmodule

Day 2/2:1mux/twotoone_tb.v
module twotoone_tb();
reg in1,in2;
reg sel;
wire out;

twotoone uut(.in1(in1),.in2(in2),.sel(sel),.out(out));

initial begin
	$dumpfile("waves.vcd");
	$dumpvars;
end
integer i;
initial 
begin
	$monitor("time=%d in1=%b in2=%b sel=%b out=%b",$time,in1,in2,sel,out);
	sel=0;in1=0;in2=0;#10;
	sel=0;in1=0;in2=1;#10;
	sel=0;in1=1;in2=0;#10;
	sel=0;in1=1;in2=1;#10;
	sel=1;in1=0;in2=0;#10;
	sel=1;in1=0;in2=1;#10;
	sel=1;in1=1;in2=0;#10;
	sel=1;in1=1;in2=1;#10;
$finish;
end
endmodule

Day 2/2:1mux/waves.vcd
$date
	Fri Jan 24 18:42:35 2025
$end
$version
	Icarus Verilog
$end
$timescale
	1s
$end
$scope module twotoone_tb $end
$var wire 1 ! out $end
$var reg 1 " in1 $end
$var reg 1 # in2 $end
$var reg 1 $ sel $end
$scope module uut $end
$var wire 1 " in1 $end
$var wire 1 # in2 $end
$var wire 1 $ sel $end
$var wire 1 ! out $end
$upscope $end
$upscope $end
$enddefinitions $end
$comment Show the parameter values. $end
$dumpall
$end
#0
$dumpvars
0$
0#
0"
0!
$end
#10
1#
#20
1!
0#
1"
#30
1#
#40
0!
0#
0"
1$
#50
1!
1#
#60
0!
0#
1"
#70
1!
1#
