Day 2/Full_subtractor/Full_subtractor.v
module Half_subtractor(
input a,b,
output diff,borrow);

assign diff=(a^b);
assign borrow=(~a&b);
endmodule

module Full_subtractor(
input a,b,c,
output diff,borrow
    );
    wire w1,w2,w3;
    
    Half_subtractor HB1(.a(a),.b(b),.diff(w1),.borrow(w2));
    Half_subtractor HB2(.a(w1),.b(c),.diff(diff),.borrow(w3));
  or OR1(borrow,w2,w3);
 
endmodule

Verilog/Day 2/Full_subtractor/Full_subtractor_tb.v
// Code your testbench here
// or browse Examples
module Full_subtractor_tb();
reg a,b,c;
wire diff,borrow;
    
  Full_subtractor uut(.a(a),.b(b),.c(c),.diff(diff),.borrow(borrow));
    
initial begin
$dumpfile("waves.vcd");
$dumpvars(0,Full_subtractor_tb);
end
initial begin
  $monitor("Time=%0t | a=%b, b=%b c=%b | diff=%b, borrow=%b", $time, a, b,c, diff, borrow); 
a=0; b=0; c=0; #10;
a=0; b=0; c=1; #10;
a=0; b=1; c=0; #10;
a=0; b=1; c=1; #10;
a=1; b=0; c=0; #10;
a=1; b=0; c=1; #10;
a=1; b=1; c=0; #10;
a=1; b=1; c=1; #10;

$finish;
end
endmodule

Day 2/Full_subtractor/waves.vcd
$date
	Fri Jan 24 11:42:40 2025
$end
$version
	Icarus Verilog
$end
$timescale
	1s
$end
$scope module Full_subtractor_tb $end
$var wire 1 ! diff $end
$var wire 1 " borrow $end
$var reg 1 # a $end
$var reg 1 $ b $end
$var reg 1 % c $end
$scope module uut $end
$var wire 1 # a $end
$var wire 1 $ b $end
$var wire 1 " borrow $end
$var wire 1 % c $end
$var wire 1 & w3 $end
$var wire 1 ' w2 $end
$var wire 1 ( w1 $end
$var wire 1 ! diff $end
$scope module HB1 $end
$var wire 1 # a $end
$var wire 1 $ b $end
$var wire 1 ' borrow $end
$var wire 1 ( diff $end
$upscope $end
$scope module HB2 $end
$var wire 1 ( a $end
$var wire 1 % b $end
$var wire 1 & borrow $end
$var wire 1 ! diff $end
$upscope $end
$upscope $end
$upscope $end
$enddefinitions $end
$comment Show the parameter values. $end
$dumpall
$end
#0
$dumpvars
0(
0'
0&
0%
0$
0#
0"
0!
$end
#10
1"
1!
1&
1%
#20
0&
1(
1'
0%
1$
#30
0!
1%
#40
0"
1!
0'
0%
0$
1#
#50
0!
1%
#60
0(
0%
1$
#70
1"
1!
1&
1%
